LICENSE
MANIFEST.in
NOTICE.md
README.md
pyproject.toml
setup.py
integreat_cms/__init__.py
integreat_cms/integreat-cms-cli
integreat_cms/webpack-stats.json
integreat_cms.egg-info/PKG-INFO
integreat_cms.egg-info/SOURCES.txt
integreat_cms.egg-info/dependency_links.txt
integreat_cms.egg-info/requires.txt
integreat_cms.egg-info/top_level.txt
integreat_cms/_manifest/spdx_2.2/manifest.spdx.json
integreat_cms/api/__init__.py
integreat_cms/api/apps.py
integreat_cms/api/decorators.py
integreat_cms/api/urls.py
integreat_cms/api/middleware/__init__.py
integreat_cms/api/middleware/json_debug_toolbar_middleware.py
integreat_cms/api/v3/__init__.py
integreat_cms/api/v3/events.py
integreat_cms/api/v3/imprint.py
integreat_cms/api/v3/languages.py
integreat_cms/api/v3/location_categories.py
integreat_cms/api/v3/locations.py
integreat_cms/api/v3/offers.py
integreat_cms/api/v3/pages.py
integreat_cms/api/v3/pdf_export.py
integreat_cms/api/v3/push_notifications.py
integreat_cms/api/v3/regions.py
integreat_cms/api/v3/social_media_headers.py
integreat_cms/api/v3/chat/__init__.py
integreat_cms/api/v3/chat/user_chat.py
integreat_cms/api/v3/chat/utils/__init__.py
integreat_cms/api/v3/chat/utils/chat_bot.py
integreat_cms/api/v3/feedback/__init__.py
integreat_cms/api/v3/feedback/event_feedback.py
integreat_cms/api/v3/feedback/event_list_feedback.py
integreat_cms/api/v3/feedback/imprint_page_feedback.py
integreat_cms/api/v3/feedback/legacy_feedback_endpoint.py
integreat_cms/api/v3/feedback/map_feedback.py
integreat_cms/api/v3/feedback/offer_feedback.py
integreat_cms/api/v3/feedback/offer_list_feedback.py
integreat_cms/api/v3/feedback/page_feedback.py
integreat_cms/api/v3/feedback/poi_feedback.py
integreat_cms/api/v3/feedback/region_feedback.py
integreat_cms/api/v3/feedback/search_result_feedback.py
integreat_cms/api/v3/templates/error_headers.html
integreat_cms/api/v3/templates/social_media_headers.html
integreat_cms/api/v3/templates/webapp_server_side_include.html
integreat_cms/cms/__init__.py
integreat_cms/cms/admin.py
integreat_cms/cms/apps.py
integreat_cms/cms/auth.py
integreat_cms/cms/decorators.py
integreat_cms/cms/linklists.py
integreat_cms/cms/rules.py
